{
"THEUPBG": "thing",
"TKPWROEPB": "grown",
"PWHRUS": "blues",
"THEUPBS": "thins",
"PWHRU/ER": "bluer",
"RAOEUT": "right",
"PAORD": "board",
"AF": "after",
"ROEURD": "rider",
"THEUBG": "thick",
"THEZ": "these",
"THR": "there",
"PWOETS": "boats",
"THAEUR": "their",
"THAPBG": "thank",
"TKPWRO*ES": "grows",
"RAOEUDZ": "rides",
"TELS": "tells",
"OEPS": "opens",
"KWRA*ERS": "areas",
"TPAEUFD": "faced",
"WOPL": "woman",
"PAEUB": "maybe",
"PWOEPBS": "bones",
"TAERS": "tears",
"PWAOBGS": "books",
"OERLD": "older",
"TAOEPLS": "teams",
"TPAEUFS": "faces",
"TAOEFP": "teach",
"PWAOTS": "boots",
"WRAPS": "wraps",
"TPABGZ": "facts",
"WHAOEL": "wheel",
"TPAEUDZ": "fades",
"TPAEUD/-D": "faded",
"WEUPL": "women",
"PWORD": "bored",
"TAUBGS": "talks",
"HOUS": "house",
"REFTS": "rests",
"TAEURBG": "taker",
"HRAF": "laugh",
"TAEPB": "taken",
"TAEUBGS": "takes",
"TAEUBL": "table",
"HAOUPBLG/ER": "huger",
"TPAEULS": "fails",
"HAOEUDZ": "hides",
"RE/PHREU": "reply"
}
