{
"KPA/AEU": "A",
"KWRUPBG": "young",
"KPA/PHAPB": "Man",
"H": "had",
"PW-PB": "been",
"KAUT": "caught",
"TPH": "in",
"AEU": "a",
"TKAEURG": "daring",
"ABGT": "act",
"-F": "of",
"THEFT": "theft",
"SKP": "and",
"H": "had",
"PW-PB": "been",
"KAUPB/TKEPL/-D": "condemned",
"TO": "to",
"-B": "be",
"SKAOUTD": "executed",
"TPOR": "for",
"T TP-PL": "it.",
"KPA/HE": "He",
"EBGS/PREFD": "expressed",
"HEUS": "his",
"STKAOEUR": "desire",
"TO": "to",
"SAOE": "see",
"HEUS": "his",
"KPA/PHOER KW-BG": "Mother,",
"SKP": "and",
"TO": "to",
"SPAOEBG": "speak",
"W": "with",
"HER": "her",
"PW-F": "before",
"HE": "he",
"WAS": "was",
"HRED": "led",
"TO": "to",
"SKAOUGS KW-BG": "execution,",
"SKP": "and",
"-F": "of",
"KORS": "course",
"TH": "this",
"WAS": "was",
"TKPWRAPBTD TP-PL": "granted.",
"KPA/WHEPB": "When",
"HEUS": "his",
"KPA/PHOER": "Mother",
"KAEUPL": "came",
"TO": "to",
"HEUPL": "him",
"HE": "he",
"SAEUD STPH-FPLT": "said:",
"KR-GS EU": "\"I",
"WAPBT": "want",
"TO": "to",
"WEUS/PER": "whisper",
"TO": "to",
"U KW-BG KR-GS": "you,\"",
"SKP": "and",
"WHEPB": "when",
"SHE": "she",
"PWRAUT": "brought",
"HER": "her",
"AOER": "ear",
"TPHAOER": "near",
"HEUPL KW-BG": "him,",
"HE": "he",
"TPHAOERL": "nearly",
"PWEUT": "bit",
"T": "it",
"OF TP-PL": "off.",
"KPA/AUL": "All",
"-T": "the",
"PWEU/STAPB/ERS": "bystanders",
"WR": "were",
"HOR/TPAOEUD KW-BG": "horrified,",
"SKP": "and",
"SK-D": "asked",
"HEUPL": "him",
"WHA": "what",
"HE": "he",
"KO": "could",
"PHAOEPB": "mean",
"PWEU": "by",
"SUFP": "such",
"PWRAOULT": "brutal",
"SKP": "and",
"EUPB/HAOUPL": "inhuman",
"KUBGT TP-PL": "conduct.",
"KR-GS KPA/T": "\"It",
"S": "is",
"TO": "to",
"P-RB": "punish",
"HER KW-BG KR-GS": "her,\"",
"HE": "he",
"SAEUD TP-PL": "said.",
"KR-GS KPA/WHEPB": "\"When",
"EU": "I",
"WAS": "was",
"KWRUPBG": "young",
"EU": "I",
"TKPWAPB": "began",
"W": "with",
"STAELG": "stealing",
"HREUL": "little",
"THEUPBGS KW-BG": "things,",
"SKP": "and",
"PWRAUT": "brought",
"THEPL": "them",
"HOEPL": "home",
"TO": "to",
"KPA/PHOER TP-PL": "Mother.",
"KPA/STPHED": "Instead",
"-F": "of",
"RE/PWAOUBG/-G": "rebuking",
"SKP": "and",
"P-RBG": "punishing",
"PHE KW-BG": "me,",
"SHE": "she",
"HRAFD": "laughed",
"SKP": "and",
"SAEUD STPH-FPLT": "said:",
"KR-GS KPA/T": "\"It",
"HR": "will",
"TPHOT": "not",
"-B": "be",
"TPH-TSD TP-PL KR-GS": "noticed.\"",
"KPA/T": "It",
"S": "is",
"PWAU": "because",
"-F": "of",
"HER": "her",
"THA": "that",
"EU": "I",
"APL": "am",
"HAOER": "here",
"TO H-PB TKAEU TP-PL KR-GS": "to-day.\"",
"KR-GS KPA/HE": "\"He",
"S": "is",
"RAOEUT KW-BG": "right,",
"WOPL KW-BG KR-GS": "woman,\"",
"SAEUD": "said",
"-T": "the",
"KPA/PRAOEFT STPH*FPLT": "Priest;",
"KR-GS -T": "\"the",
"HRO*RD": "Lord",
"HA*T": "hath",
"SAEUD STPH-FPLT": "said:",
"KR-GS KPA/TRAEUPB": "\"Train",
"UP": "up",
"AEU": "a",
"KHAOEULD": "child",
"TPH": "in",
"-T": "the",
"WAEU": "way",
"HE": "he",
"SHO": "should",
"TKPW STPH*FPLT": "go;",
"SKP": "and",
"WHEPB": "when",
"HE": "he",
"S": "is",
"OLD": "old",
"HE": "he",
"HR": "will",
"TPHOT": "not",
"TKPART": "depart",
"THR-FRPL TP-PL KR-GS": "therefrom.\""
}
