{
"XXX Gothel KW-BG": "Gothel,",
"HOU": "how",
"T": "it",
"HABS": "happens",
"THA": "that",
"U": "you",
"R": "are",
"SO": "so",
"PHUFP": "much",
"HEF/KWRER": "heavier",
"TPOR": "for",
"PHE": "me",
"TO": "to",
"TKRAU": "draw",
"UP": "up",
"THAPB": "than",
"-T": "the",
"KWRUPBG": "young",
"KEUPBG AE S*/SP-S": "king's",
"SOPB H-PB H-PB E": "son--he",
"S": "is",
"W": "with",
"PHE": "me",
"TPH": "in",
"AEU": "a",
"PHOEPLT TP-PL AE": "moment.'",
"AE HA*E SKHRAPL": "'Ah!",
"U": "you",
"WEUBGD": "wicked",
"KHAOEULD KW-BG AE": "child,'",
"KRAOEUD": "cried",
"-T": "the",
"EPB/KHAPBT/RES TP-PL": "enchantress.",
"AE WHA": "'What",
"TKO": "do",
"EU": "I",
"HAER": "hear",
"U": "you",
"SAEU SKHRAPL": "say!",
"EU": "I",
"THAUT": "thought",
"EU": "I",
"H": "had",
"SERPTD": "separated",
"U": "you",
"TPR": "from",
"AUL": "all",
"-T": "the",
"WORLD KW-BG": "world,",
"SKP": "and",
"KWRET": "yet",
"U": "you",
"SR": "have",
"TKAOE/SAOEFD": "deceived",
"PHE SKHRAPL AE": "me!'",
"TPH": "In",
"HER": "her",
"ARPBG": "anger",
"SHE": "she",
"KHRUFPD": "clutched",
"RA/PUPB/S*EL AE S*/SP-S": "Rapunzel's",
"PWAOUFL": "beautiful",
"TRESZ/-S KW-BG": "tresses,",
"WRAPD": "wrapped",
"THEPL": "them",
"TWAOEUS": "twice",
"ROUPBD": "round",
"HER": "her",
"HREFT": "left",
"HAPBD KW-BG": "hand,",
"SAOEZ/-D": "seized",
"AEU": "a",
"PAEUR": "pair",
"-F": "of",
"SEUS/ORS": "scissors",
"W": "with",
"-T": "the",
"RAOEUT KW-BG": "right,",
"SKP": "and",
"STPHEUP KW-BG": "snip,",
"STPHAP KW-BG": "snap,",
"THE": "they",
"WR": "were",
"KUT": "cut",
"OF KW-BG": "off,",
"SKP": "and",
"-T": "the",
"HROFL": "lovely",
"PWRAEUDZ": "braids",
"HRAEU": "lay",
"OPB": "on",
"-T": "the",
"TKPWROUPBD TP-PL": "ground.",
"SKP": "And",
"SHE": "she",
"WA": "was",
"SO": "so",
"PEUT/*EULS": "pitiless",
"THA": "that",
"SHE": "she",
"TAOBG": "took",
"PAOR": "poor",
"RA/PUPB/S*EL": "Rapunzel",
"TPHAO": "into",
"AEU": "a",
"STK*ERT": "desert",
"W-R": "where",
"SHE": "she",
"H": "had",
"TO": "to",
"HREUF": "live",
"TPH": "in",
"TKPWRAET": "great",
"TKPWRAOEF": "grief",
"SKP": "and",
"PHEUS/REU TP-PL": "misery.",
"OPB": "On",
"-T": "the",
"SAEUPL": "same",
"TKAEU": "day",
"THA": "that",
"SHE": "she",
"KAFT": "cast",
"OUT": "out",
"RA/PUPB/S*EL KW-BG": "Rapunzel,",
"HOUF KW-BG": "however,",
"-T": "the",
"EPB/KHAPBT/RES": "enchantress",
"TPAS/-PBD": "fastened",
"-T": "the",
"PWRAEUDZ": "braids",
"-F": "of",
"HAEUR KW-BG": "hair,",
"WEU": "which",
"SHE": "she",
"H": "had",
"KUT": "cut",
"OF KW-BG": "off,",
"TO": "to",
"-T": "the",
"HAOBG": "hook",
"-F": "of",
"-T": "the",
"WOEUPBD KW-BG": "window,",
"SKP": "and",
"WHEPB": "when",
"-T": "the",
"KEUPBG AE S*/SP-S": "king's",
"SOPB": "son",
"KAEUPL": "came",
"SKP": "and",
"KRAOEUD STPH-FPLT": "cried:",
"AE RA/PUPB/S*EL KW-BG": "'Rapunzel,",
"RA/PUPB/S*EL KW-BG": "Rapunzel,",
"HRET": "Let",
"TKOUPB": "down",
"KWROUR": "your",
"HAEUR": "hair",
"TO": "to",
"PHE TP-PL AE": "me.'",
"SHE": "she",
"HRET": "let",
"-T": "the",
"HAEUR": "hair",
"TKOUPB TP-PL": "down.",
"-T": "The",
"KEUPBG AE S*/SP-S": "king's",
"SOPB": "son",
"A/SEPBD/-D KW-BG": "ascended,",
"PWUT": "but",
"STPHED": "instead",
"-F": "of",
"TPAOEPBGD": "finding",
"HEUS": "his",
"TKAER/EFT": "dearest",
"RA/PUPB/S*EL KW-BG": "Rapunzel,",
"E": "he",
"TPOUPBD": "found",
"-T": "the",
"EPB/KHAPBT/RES KW-BG": "enchantress,",
"WHO": "who",
"TKPWAEZ/-D": "gazed",
"AT": "at",
"HEUPL": "him",
"W": "with",
"WEUBGD": "wicked",
"SKP": "and",
"SREPB/PHOUS": "venomous",
"HAOBGS TP-PL": "looks.",
"AE XXX Aha SKHRAPL AE": "'Aha!'",
"SHE": "she",
"KRAOEUD": "cried",
"PHOBG/-G/HREU KW-BG": "mockingly,",
"AE U": "'you",
"WO": "would",
"TPEFP": "fetch",
"KWROUR": "your",
"TKAER/EFT KW-BG": "dearest,",
"PWUT": "but",
"-T": "the"
}
