{
"T": "it",
"WA": "was",
"U KW-BG": "you,",
"WOEUPL KW-BG": "William,",
"WHO": "who",
"H": "had",
"AEU": "a",
"PHAOEUPBD": "mind",
"TO": "to",
"HRUZ": "lose",
"THEPL STPH*FPLT": "them;",
"EU": "I",
"TOLD": "told",
"U": "you",
"WE": "we",
"SHO": "should",
"XXX repent": "repent",
"-F": "of",
"T STPH-FPLT": "it:",
"WHA": "what",
"R": "are",
"THE": "they",
"TPHOU": "now",
"TK*G": "doing",
"TPH": "in",
"-T": "the",
"TPOEFRT H-F": "forest?",
"A/HRAS SKHRAPL": "Alas!",
"TKAER": "dear",
"TKPWOD KW-BG": "God,",
"-T": "the",
"WOFLS": "wolves",
"SR KW-BG": "have,",
"PRAPS KW-BG": "perhaps,",
"HR-R": "already",
"AOET/EPB": "eaten",
"THEPL": "them",
"UP STPH-FPLT": "up:",
"THO*U": "thou",
"ART": "art",
"SRE": "very",
"XXX inhuman": "inhuman",
"THUS": "thus",
"TO": "to",
"SR": "have",
"HRO*S": "lost",
"THAO*EU": "thy",
"KHEURPB TP-PL KR-GS": "children.\"",
"-T": "The",
"TPAGT H-PB PHAEURBG": "faggot-maker",
"TKPWRAOU": "grew",
"AT": "at",
"HRAFT": "last",
"KWAOEUT": "quite",
"OUT": "out",
"-F": "of",
"PAEURBS KW-BG": "patience,",
"TPOR": "for",
"SHE": "she",
"RE/PAOETD": "repeated",
"TH": "this",
"PWOF": "above",
"TWEPBT": "twenty",
"TAOEUPLS KW-BG": "times,",
"THA": "that",
"THE": "they",
"SHO": "should",
"XXX repent": "repent",
"-F": "of",
"T KW-BG": "it,",
"SKP": "and",
"SHE": "she",
"WA": "was",
"TPH": "in",
"-T": "the",
"RAOEUT": "right",
"-F": "of",
"T": "it",
"TPOR": "for",
"SO": "so",
"SAEUG TP-PL": "saying.",
"E": "He",
"THREFPBD": "threatened",
"TO": "to",
"PWAET": "beat",
"HER KW-BG": "her,",
"TP": "if",
"SHE": "she",
"TK": "did",
"TPHOT": "not",
"HOLD": "hold",
"HER": "her",
"TUPBG TP-PL": "tongue.",
"T": "It",
"WA": "was",
"TPHOT": "not",
"THA": "that",
"-T": "the",
"TPAGT H-PB PHAEURBG": "faggot-maker",
"WA": "was",
"TPHOT KW-BG": "not,",
"PRAPS KW-BG": "perhaps,",
"PHOR": "more",
"SREBGS/-D": "vexed",
"THAPB": "than",
"HEUS": "his",
"WAOEUF KW-BG": "wife,",
"PWUT": "but",
"THA": "that",
"SHE": "she",
"XXX teized": "teized",
"HEUPL KW-BG": "him,",
"SKP": "and",
"THA": "that",
"E": "he",
"WA": "was",
"-F": "of",
"-T": "the",
"HAOURPL": "humour",
"-F": "of",
"AEU": "a",
"TKPWRAET": "great",
"PHAEPB": "many",
"OERS KW-BG": "others,",
"WHO": "who",
"HRUF": "love",
"WEUFS": "wives",
"WHO": "who",
"SPAOEBG": "speak",
"RAOEUT KW-BG": "right,",
"PWUT": "but",
"THEU": "think",
"THOZ": "those",
"SRE": "very",
"XXX importunate": "importunate",
"WHO": "who",
"R": "are",
"AULZ": "always",
"TPH": "in",
"-T": "the",
"RAOEUT TP-PL": "right.",
"SHE": "She",
"WA": "was",
"HAF": "half",
"TKROUPBD": "drowned",
"TPH": "in",
"TAERS KW-BG": "tears,",
"KRAOEUG": "crying",
"OUT STPH-FPLT": "out:",
"KR-GS A/HRAS SKHRAPL": "\"Alas!",
"W-R": "where",
"R": "are",
"TPHOU": "now",
"PHEU": "my",
"KHEURPB KW-BG": "children,",
"PHEU": "my",
"PAOR": "poor",
"KHEURPB H-F KR-GS": "children?\"",
"SHE": "She",
"XXX spake": "spake",
"TH": "this",
"SO": "so",
"SRE": "very",
"HROUD KW-BG": "loud,",
"THA": "that",
"-T": "the",
"KHEURPB": "children",
"WHO": "who",
"WR": "were",
"AT": "at",
"-T": "the",
"TKAOR KW-BG": "door,",
"TKPWAPB": "began",
"TO": "to",
"KRAOEU": "cry",
"OUT": "out",
"AUL": "all",
"TOGT STPH-FPLT": "together:",
"KR-GS HAOER": "\"Here",
"WE": "we",
"R KW-BG": "are,",
"HAOER": "here",
"WE": "we",
"R TP-PL KR-GS": "are.\"",
"SHE": "She",
"RAPB": "ran",
"PHAOELD": "immediately",
"TO": "to",
"OEP": "open",
"-T": "the",
"TKAOR KW-BG": "door,",
"SKP": "and",
"SAEUD KW-BG": "said,",
"HUG/-G": "hugging",
"THEPL STPH-FPLT": "them:",
"KR-GS EU": "\"I",
"APL": "am",
"TKPWHRAD": "glad",
"TO": "to",
"SAOE": "see"
}
