{
"TPH": "In",
"TKEPB/PHARBG": "Denmark",
"THR": "there",
"STAPBDZ": "stands",
"APB": "an",
"OLD": "old",
"KAFL": "castle",
"TPHAEUPLD": "named",
"XXX Kronenburg KW-BG": "Kronenburg,",
"KHROES": "close",
"PWEU": "by",
"-T": "the",
"SOUPBD": "Sound",
"-F": "of",
"XXX Elsinore KW-BG": "Elsinore,",
"W-R": "where",
"HRARPBLG": "large",
"SHEUPS KW-BG": "ships,",
"PWO*T": "both",
"TPWHREURB KW-BG": "English,",
"R*UGS KW-BG": "Russian,",
"SKP": "and",
"PRUGS KW-BG": "Prussian,",
"PAS": "pass",
"PWEU": "by",
"HUPBS": "hundreds",
"EF": "every",
"TKAEU TP-PL": "day.",
"SKP": "And",
"THE": "they",
"SA/HRAOUT": "salute",
"-T": "the",
"OLD": "old",
"KAFL": "castle",
"W": "with",
"KAPB/TPHOPB/-S KW-BG": "cannons,",
"KR-GS PWAOPL KW-BG": "\"Boom,",
"PWAOPL KW-BG KR-GS": "boom,\"",
"WEU": "which",
"S": "is",
"AZ": "as",
"TP": "if",
"THE": "they",
"SAEUD KW-BG": "said,",
"KR-GS TKPWAOD H-PB TKAEU TP-PL KR-GS": "\"Good-day.\"",
"SKP": "And",
"-T": "the",
"KAPB/TPHOPB/-S": "cannons",
"-F": "of",
"-T": "the",
"OLD": "old",
"KAFL": "castle",
"AEPBS": "answer",
"KR-GS PWAOPL KW-BG KR-GS": "\"Boom,\"",
"WEU": "which",
"PHAOEPBS": "means",
"KR-GS PHAEPB": "\"Many",
"THAPBGS TP-PL KR-GS": "thanks.\"",
"TPH": "In",
"WEURPBT": "winter",
"TPHO": "no",
"SHEUPS": "ships",
"SAEUL": "sail",
"PWEU KW-BG": "by,",
"TPOR": "for",
"-T": "the",
"WHOEL": "whole",
"SOUPBD": "Sound",
"S": "is",
"KOFRD": "covered",
"W": "with",
"AOEUS": "ice",
"AZ": "as",
"TPAR": "far",
"AZ": "as",
"-T": "the",
"SWAOED/EURB": "Swedish",
"KOEFT KW-BG": "coast,",
"SKP": "and",
"HAS": "has",
"KWAOEUT": "quite",
"-T": "the",
"PAOERPBS": "appearance",
"-F": "of",
"AEU": "a",
"HAOEU H-PB RAOD TP-PL": "high-road.",
"-T": "The",
"TKAEUPB/EURB": "Danish",
"SKP": "and",
"-T": "the",
"SWAOED/EURB": "Swedish",
"TPHRAGS": "flags",
"WAF KW-BG": "wave,",
"SKP": "and",
"TKA*EUPB/-S": "Danes",
"SKP": "and",
"SWAOED/-S": "Swedes",
"SAEU KW-BG": "say,",
"KR-GS TKPWAOD H-PB TKAEU KW-BG KR-GS": "\"Good-day,\"",
"SKP": "and",
"KR-GS THAPBG": "\"Thank",
"U KR-GS": "you\"",
"TO": "to",
"AOEFP": "each",
"OER KW-BG": "other,",
"TPHOT": "not",
"W": "with",
"KAPB/TPHOPB/-S KW-BG": "cannons,",
"PWUT": "but",
"W": "with",
"AEU": "a",
"TPREPBLD": "friendly",
"SHAEUBG": "shake",
"-F": "of",
"-T": "the",
"HAPBD STPH*FPLT": "hand;",
"SKP": "and",
"THE": "they",
"KPAEUPBG": "exchange",
"WHAOEUT": "white",
"PWRAED": "bread",
"SKP": "and",
"PWEUFBGT/-S": "biscuits",
"W": "with",
"AOEFP": "each",
"OER KW-BG": "other,",
"PWAU": "because",
"TPOERP": "foreign",
"ARLS": "articles",
"TAEUFT": "taste",
"-T": "the",
"PWEFT TP-PL": "best.",
"PWUT": "But",
"-T": "the",
"PHOFT": "most",
"PWAOUFL": "beautiful",
"SAOEUT": "sight",
"-F": "of",
"AUL": "all",
"S": "is",
"-T": "the",
"OLD": "old",
"KAFL": "castle",
"-F": "of",
"XXX Kronenburg KW-BG": "Kronenburg,",
"W-R": "where",
"XXX Holger": "Holger",
"XXX Danske": "Danske",
"SEUTS": "sits",
"TPH": "in",
"-T": "the",
"TKAOEP KW-BG": "deep,",
"TKARBG": "dark",
"SEL/AR KW-BG": "cellar,",
"TPHAO": "into",
"WEU": "which",
"TPHO": "no",
"WUPB": "one",
"TKPW-S TP-PL": "goes.",
"E": "He",
"S": "is",
"KHRAD": "clad",
"TPH": "in",
"AOEURPB": "iron",
"SKP": "and",
"STAOEL KW-BG": "steel,",
"SKP": "and",
"REFTS": "rests",
"HEUS": "his",
"HED": "head",
"OPB": "on",
"HEUS": "his",
"STROPBG": "strong",
"ARPL STPH*FPLT": "arm;",
"HEUS": "his",
"HROPBG": "long",
"PWAERD": "beard",
"HAPBGS": "hangs",
"TKOUPB": "down",
"POPB": "upon",
"-T": "the",
"PHAERBL": "marble",
"TAEUBL KW-BG": "table,",
"TPHAO": "into",
"WEU": "which",
"T": "it",
"HAS": "has",
"PW-BG": "become",
"TPEURPL/HREU": "firmly",
"RAOT/-D STPH*FPLT": "rooted;",
"E": "he",
"SHRAOEPS": "sleeps",
"SKP": "and",
"TKRAOEPLS KW-BG": "dreams,",
"PWUT": "but",
"TPH": "in",
"HEUS": "his",
"TKRAOEPLS": "dreams",
"E": "he",
"SAO*ES": "sees"
}
