{
"TPAEUD": "fade",
"TPAEUL": "fail",
"SEUBG": "sick",
"PWO*T": "both",
"TAEUBG": "take",
"HRAOEPB": "lean",
"KEUBG": "kick",
"TPH*UPL": "numb",
"REFT": "rest",
"HOEL": "hole",
"TKPWEUFT": "gift",
"SHUT": "shut",
"HED": "head",
"TPEL": "fell",
"TPAUL": "fall",
"TKO/ER": "doer",
"KEPT": "kept",
"TKPWEUS": "guys",
"HAEUR": "hair",
"KWREL": "yell",
"TKOGS": "dogs",
"PWOEUS": "boys",
"WAOEUPB": "wine",
"SHOE": "show",
"SKWROBS": "jobs",
"PAOEUL": "pile",
"HRAOEF": "leaf",
"SHUR": "sure",
"TPA*S": "fast",
"TKAOR": "door",
"TPAOER": "fear",
"WORD": "word",
"ABL": "able",
"HAF": "half",
"TPAOES": "fees",
"WHEPB": "when",
"TKOUPB": "down",
"AOEUS/-D": "iced",
"TPEDZ": "feds",
"TKPWEURL": "girl",
"PHAOEUPB": "mine",
"TPAOED": "feed",
"HAER": "hear",
"TKRAG": "drag",
"SAOUT": "suit",
"WEUPBG": "wing",
"TPELT": "felt",
"TKPWEUF": "give",
"SHOP": "shop",
"TKRAU": "draw"
}
