{
"TPEUT": "fit",
"WAEU": "way",
"RED": "red",
"TPAOE": "fee",
"TPED": "fed",
"SK": "ask",
"REUD": "rid",
"AOEU": "eye",
"ROE": "row",
"RUB": "rub",
"RUPB": "run",
"RAPB": "ran",
"SAD": "sad",
"SAEU": "say",
"EPBD": "end",
"EG": "egg",
"SAE": "sea",
"WOPB": "won",
"WEUPB": "win",
"SAU": "saw",
"SAOE": "see",
"AOET": "eat",
"AEUT": "ate",
"AOER": "ear",
"SET": "set",
"S-BGS": "sex",
"TKRAOEU": "dry",
"SHE": "she",
"TKOG": "dog",
"TK": "did",
"TKAOEU": "die",
"SEUR": "sir",
"SAT": "sat",
"SEUT": "sit",
"KWR": "why",
"SEUBGS": "six",
"TKAEU": "day",
"SKAOEU": "sky",
"TKAD": "dad",
"WHO": "who",
"KUT": "cut",
"KUP": "cup",
"KRAOEU": "cry",
"SO*S": "SOS",
"KOP": "cop",
"SOPB": "son",
"SKP": "and",
"KAT": "cat",
"KAR": "car",
"K": "can"
}
