{
"KPA/TPH": "In",
"TKEPB/PHARBG": "Denmark",
"THR": "there",
"STAPBDZ": "stands",
"APB": "an",
"OLD": "old",
"KAFL": "castle",
"TPHAEUPLD": "named",
"K*P/R*/KWRO/*PB/*EPB/PW*URG/KW-BG": "Kronenburg,",
"KHROES": "close",
"PWEU": "by",
"-T": "the",
"KPA/SOUPBD": "Sound",
"-F": "of",
"EL/-S/*EUPB/O*R/SKWR*E/KW-BG": "Elsinore,",
"W-R": "where",
"HRARPBLG": "large",
"SHEUPS/KW-BG": "ships,",
"PWO*T": "both",
"EPBG/HREUBG/HREURB/-RBGS": "English,",
"R*UGS/KW-BG": "Russian,",
"SKP": "and",
"PRUGS/KW-BG": "Prussian,",
"PAS": "pass",
"HUPBS": "hundreds",
"EF": "every",
"TKAEU/TP-PL": "day.",
"AFPBD": "And",
"THE": "they",
"SA/HRAOUT": "salute",
"W": "with",
"KAPB/TPHOPB/-S/KW-BG": "cannons,",
"KW-GS/KPA*/PWAOPL/KW-BG": "\"Boom,",
"PWAOPL/KW-BG/KR-GS": "boom,\"",
"WEU": "which",
"S": "is",
"AS": "as",
"TP": "if",
"SED/KW-BG": "said,",
"KW-GS/KPA*/TKPWAOD/H-PB/TKAEU/TP-PL/KR-GS": "\"Good-day.\"",
"KAPB/TPHOPB/-S": "cannons",
"AEPBS": "answer",
"KW-GS/KPA*/PWAOPL/KW-BG/KR-GS": "\"Boom,\"",
"PHAOEPBS": "means",
"KW-GS/KPA*/PHAEPB": "\"Many",
"THAPBGS/TP-PL/KR-GS": "thanks.\"",
"WEURPBT": "winter",
"TPHO": "no",
"SHEUPS": "ships",
"SAEUL": "sail",
"PWEU/KW-BG": "by,",
"TPOR": "for",
"WHOEL": "whole",
"KOFRD": "covered",
"AOEUS": "ice",
"TPAR": "far",
"SWAOED/EURB": "Swedish",
"KOEFT/KW-BG": "coast,",
"HAS": "has",
"KWAOEUT": "quite",
"PAOERPBS": "appearance",
"AEU": "a",
"HAOEU/H-PB/RAOD/TP-PL": "high-road.",
"KPA/-T": "The",
"TKAEUPB/EURB": "Danish",
"TPHRAGS": "flags",
"WAF/KW-BG": "wave,",
"TKA*EUPB/-S": "Danes",
"SWAOED/-S": "Swedes",
"SAEU/KW-BG": "say,",
"KW-GS/KPA/TKPWAOD/TKA*EU/KW-BG/KR-GS": "\"Good-day,\"",
"KW-GS/KPA*/THAPBG": "\"Thank",
"U/KR-GS": "you\"",
"TO": "to",
"AOEFP": "each",
"OER/KW-BG": "other,",
"TPHOT": "not",
"PWUT": "but",
"TPREPBLD": "friendly",
"SHAEUBG": "shake",
"HAPBD/STPH*FPLT": "hand;",
"KPAEUPBG": "exchange",
"WHAOEUT": "white",
"PWRAED": "bread",
"PWEUFBGT/-S": "biscuits",
"PWAU": "because",
"TPOERPB": "foreign",
"ARLS": "articles",
"TAEUFT": "taste",
"PWEFT/TP-PL": "best.",
"KPA/PWUT": "But",
"PHOFT": "most",
"PWAOUFL": "beautiful",
"SAOEUT": "sight",
"AUL": "all",
"H*P/O*/HR*/TKPW*/*ER": "Holger",
"TKAPB/-S/*BG/SKWR*E": "Danske",
"SEUTS": "sits",
"TPH": "in",
"TKAOEP/KW-BG": "deep,",
"TKARBG": "dark",
"SEL/AR/KW-BG": "cellar,",
"TPHAO": "into",
"WUPB": "one",
"TKPW-S/TP-PL": "goes.",
"KPA/HE": "He",
"KHRAD": "clad",
"AOEURPB": "iron",
"STAOEL/KW-BG": "steel,",
"REFTS": "rests",
"HEUS": "his",
"HED": "head",
"OPB": "on",
"STROPBG": "strong",
"ARPL/STPH*FPLT": "arm;",
"HROPBG": "long",
"PWAERD": "beard",
"HAPBGS": "hangs",
"TKOUPB": "down",
"POPB": "upon",
"PHAERBL": "marble",
"TAEUBL/KW-BG": "table,",
"T": "it",
"PW-BG": "become",
"TPEURPL/HREU": "firmly",
"RAOT/-D/STPH*FPLT": "rooted;",
"HE": "he",
"SHRAOEPS": "sleeps",
"TKRAOEPLS/KW-BG": "dreams,",
"TKRAOEPLS": "dreams",
"SAO*ES": "sees",
"EFRG": "everything",
"THA": "that",
"HAPS": "happens",
"TKEPB/PHARBG/TP-PL": "Denmark.",
"KPA/OPB": "On",
"KREUS/PHAS/H-PB/HRO*ER/AOEF": "Christmas-eve",
"APB/SKWREL": "angel",
"KOPLS": "comes",
"HEUPL": "him",
"TELS": "tells",
"TKREPLD": "dreamed",
"TRAOU/KW-BG": "true,",
"PHAE": "may",
"TKPW": "go",
"SHRAOEP": "sleep",
"TKPWEPB": "again",
"PAES/KW-BG": "peace,",
"KWRET": "yet",
"TPHEU": "any",
"RAEL": "real",
"TKAEUPBLG/STPH*FPLT": "danger;",
"SHO": "should",
"TKAEUPBLG": "danger",
"-FR": "ever",
"KOPL/KW-BG": "come,",
"THEPB": "then",
"HR": "will",
"ROUZ": "rouse",
"HEUPLS/KW-BG": "himself,",
"TAEUBL": "table",
"PWUFRT": "burst",
"AS/UPBD/ER": "asunder",
"TKRAUS": "draws",
"OUT": "out",
"PWAERD/TP-PL": "beard.",
"KPA/THEPB": "Then",
"KOPL": "come",
"TPO*RT": "forth",
"STREPBG/KW-BG": "strength,",
"STRAOEUBG": "strike",
"PWHROE": "blow",
"SHAL": "shall",
"SOUPBD": "sound",
"KUPBTS": "countries",
"WORLD/TP-PL": "world.",
"KPA/APB": "An",
"TKPWR-F": "grandfather",
"SAT": "sat",
"TOLD": "told",
"HREUL": "little",
"TKPWR-S": "grandson",
"TH": "this",
"PW": "about",
"TKAPB/-S/*BG/SKWR*E/KW-BG": "Danske,",
"PWOEU": "boy",
"TPHAOU": "knew",
"WHA": "what",
"PHUFT": "must",
"-B": "be",
"TRAOU/TP-PL": "true.",
"KPA/AS": "As",
"PHAPB": "man",
"RAELTD": "related",
"STOER/KW-BG": "story,",
"WAS": "was",
"KAFRBG": "carving",
"EUPBLG": "image",
"WAOD": "wood",
"REPT": "represent",
"TPAS/-PBD": "fastened",
"PRO*U": "prow",
"SHEUP/STPH*FPLT": "ship;",
"KAFRB/ER": "carver",
"WAOD/KW-BG": "wood,",
"S-RBGS": "is,",
"WHO": "who",
"KAFRBD": "carved",
"TPEUGS": "figures",
"HEDZ": "heads",
"KORG": "according",
"TPHAEUPLS": "names",
"TKPWEUFPB": "given",
"THEPL/TP-PL": "them.",
"TPHOU": "now",
"H": "had",
"STAOD": "stood",
"ER/EBGT": "erect",
"PROUD/KW-BG": "proud,",
"PWAERD/KW-BG": "beard,",
"HOELGD": "holding",
"HAPBD": "hand",
"PWRAOD": "broad",
"PWA*LT/H-PB/ABGS/KW-BG": "battle-axe,",
"WHAOEUL": "while",
"OER": "other",
"HRAOEPBD": "leaned",
"ARPLS/TP-PL": "arms.",
"TKPWRAET": "great",
"TKAOEL": "deal",
"PHEPB": "men",
"WEUPL": "women",
"STKPWAOURBD": "distinguished",
"TH*EPLS": "themselves",
"OLD/*EPB": "olden",
"TAOEUPLS/KW-BG": "times,",
"SO": "so",
"TPAPB/SEU/-D": "fancied",
"PHUFP": "much",
"AOEPB": "even",
"WHO/KW-BG": "who,",
"AF": "after",
"AUL/KW-BG": "all,",
"KO": "could",
"OEPBL": "only",
"TKRAOEPL/STPH*FPLT": "dream;",
"WHEPB": "when",
"TP*EL": "fellow",
"WEPBT": "went",
"PWED/KW-BG": "bed,",
"THAUT": "thought",
"TAOULT": "actually",
"PREFD": "pressed",
"KHEUPB": "chin",
"TKPWEPBS": "against",
"KOUFRPBT/PAEPB/KW-BG": "counterpane,",
"PHAPBLGD": "imagined",
"RAOT/-D": "rooted",
"T/TP-PL": "it.",
"RE/PHAEUPBD": "remained",
"SEUGT": "sitting",
"AT": "at",
"WORBG": "work",
"WA*EU": "away",
"HRAFT": "last",
"PART": "part",
"T/KW-BG": "it,",
"TP*EURBD": "finished",
"HRAOBGD": "looked",
"TPEUG/KW-BG": "figure,",
"HAERD": "heard",
"RAED/KW-BG": "read,",
"AOEPBG": "evening",
"TKPWR-S/TP-PL": "grandson.",
"TPHOD/-D": "nodded",
"HED/KW-BG": "head,",
"WAOEUPD": "wiped",
"SPEBGT/K-LS": "spectacles",
"PUT": "put",
"THEPL": "them",
"OPB/KW-BG": "on,",
"KW-GS/KPA*/AERBGS": "\"Ah,",
"KWRE/STPH*FPLT": "yes;",
"A/PAOER": "appear",
"PHEU": "my",
"HRAOEUF/TAOEUPL/KW-BG": "lifetime,",
"PWED": "bed",
"SRE": "very",
"HRAOEULG": "likely",
"HREUF": "live",
"SAOE": "see",
"EFPBT": "event",
"R-L": "really",
"PAS/TP-PL/KR-GS": "pass.\"",
"TKPWEPB/STPH*FPLT": "again;",
"PHOR": "more",
"SAED": "satisfied",
"TPELT": "felt",
"TKPWAOD": "good",
"HEUPL/TP-PL": "him.",
"KPA/T": "It",
"SAOEPLD": "seemed",
"TKPWHROE": "glow",
"KROR": "color",
"HRAOEUF/STPH*FPLT": "life;",
"AR/PHOR": "armor",
"TKPWHREUT/ERD": "glittered",
"HRAOEUBG": "like",
"STAOEL/TP-PL": "steel.",
"HARTS": "hearts",
"ARPLS": "arms",
"TKPWRAOU": "grew",
"RED/STPH*FPLT": "red;",
"HRAOEU/O*PBS/KW-BG": "lions,",
"TKPWOELD": "gold",
"KROUPBS": "crowns",
"THAEUR": "their",
"HEDZ/KW-BG": "heads,",
"WR": "were",
"HRAOEPG": "leaping",
"UP/TP-PL": "up.",
"KW-GS/KPA*/THA": "\"That",
"KOET": "coat",
"WORLD/KW-BG/KR-GS": "world,\"",
"SED": "said",
"PHAPB/TP-PL": "man.",
"KW-GS/KPA*/-T": "\"The",
"HRAOEU/O*PBS": "lions",
"STREPBG/STPH*FPLT": "strength;",
"HARTS/KW-BG": "hearts,",
"SKWR*EPBLT/-PBS": "gentleness",
"HRUF/TP-PL/KR-GS": "love.\"",
"TKPWAEZ/-D": "gazed",
"UP/ER/PHOEFT": "uppermost",
"HRO*EUPB/KW-BG": "lion,",
"KO*EUPBG": "King",
"KR*P/A*/TPH*/*U/T*/SKWR*E/KW-BG": "Canute,",
"KHAEUPBD": "chained",
"TKPWHRAEPBD": "England",
"TKEPB/PHARBG/AES": "Denmark's",
"THRO*EPB/STPH*FPLT": "throne;",
"SEBGD": "second",
"W*P/A*/HR*/TK*/*E/PH*/A*R/KW-BG": "Waldemar,",
"UPB/TAOEUD": "untied",
"KAUPB/KERD": "conquered",
"KPA/SRAPBD/ALS/TP-PL": "Vandals.",
"THEURD": "third",
"HRO*EUPB": "lion",
"RE/PHAOEUPBD/T-D": "reminded",
"PHARG/RET/KW-BG": "Margaret,",
"AOUPBTD": "united",
"TKEPB/PHARBG/KW-BG": "Denmark,",
"SWAOED/-PB/KW-BG": "Sweden,",
"TPHOR/WAEU/TP-PL": "Norway.",
"RED": "red",
"KHRORS": "colors",
"TKPWHROE/-D": "glowed",
"TKAO*EPL/KW-BG": "deeply,",
"TPHRAEUPLS/KW-BG": "flames,",
"PHOEURPL": "memory",
"TPOLD": "followed",
"TURPB/TP-PL": "turn.",
"TPEUFRT": "first",
"HRED": "led",
"TKARBG/KW-BG": "dark,",
"TPHO*EUR": "narrow",
"PREUZ/KW-BG": "prison,",
"PREURZ/KW-BG": "prisoner,",
"WOPL/KW-BG": "woman,",
"TKAUR": "daughter",
"KREUGS": "Christian",
"KPA/TPO*URT/KW-BG": "Fourth,",
"EL/TPHOR": "Eleanor",
"*UP/HR*/TP*/*E/HR*/TK*/KW-BG": "Ulfeld,",
"TPHRAEUPL": "flame",
"PWAEUPL": "became",
"ROEZ": "rose",
"HER": "her",
"PWUZ/OPL/KW-BG": "bosom,",
"EUTS": "its",
"PWHROS/SOPL/-S": "blossoms",
"PAOUR": "pure",
"THAPB": "than",
"HART": "heart",
"TPHOEBL/*ES": "noblest",
"PWEFT": "best",
"WEUPL/TP-PL": "women.",
"TPHAOEPBD": "indeed",
"TPHOEBL": "noble",
"ARPLS/KW-BG/KR-GS": "arms,\"",
"TKPWR-F/KW-BG": "grandfather,",
"SPEURT": "spirit",
"TPHRAEUPL/KW-BG": "flame,",
"KAERD": "carried",
"SAE/KW-BG": "sea,",
"RAORD": "roared",
"HRAEU": "lay",
"SHROUD/-D": "shrouded",
"SPHOEBG/KW-BG": "smoke,",
"TPHRAPLG": "flaming",
"A/TAFPD": "attached",
"T/SEFL": "itself",
"PWREFT": "breast",
"H*P/SR*/*EU/T*/TP*/*E/HR*/TK*/T*": "Hvitfeldt",
"TPORPL": "form",
"REUB/O*PB": "ribbon",
"ORD/KW-BG": "order,",
"PWHRAOU": "blew",
"HEUPLS": "himself",
"SHEUP": "ship",
"AEUR": "air",
"ORD": "order",
"SAF": "save",
"TPHRAOET/TP-PL": "fleet.",
"TKPWRAOEPB/HRA*PBD/AES": "Greenland's",
"WREFPD": "wretched",
"HUTS/KW-BG": "huts,",
"PRAO*EFP/KW-BG": "preacher,",
"HAPBS": "Hans",
"*EP/TKPW*/-D/SKWR*E/KW-BG": "Egede,",
"RAOULD": "ruled",
"HRUF": "love",
"WORD": "word",
"*BGS/TP-PL": "action.",
"STAR": "star",
"PWREFT/KW-BG": "breast,",
"AD/-D": "added",
"TPHOER": "another",
"TKPWR-F/AES": "grandfather's",
"TPHEGT": "next",
"HOFRG": "hovering",
"WHEU/THER": "whither",
"WO": "would",
"HRAED": "lead",
"PEFPBT": "peasant",
"WOPL/AES": "woman's",
"HUPL/-BL": "humble",
"RAOPL": "room",
"TPRED/REUBG": "Frederick",
"KPA/S*BGS/KW-BG": "Sixth,",
"WREUG": "writing",
"TPHAEUPL": "name",
"KHAUBG": "chalk",
"PWAEPL/TP-PL": "beam.",
"TREPL/-BLD": "trembled",
"HART/KW-BG": "heart,",
"PEFPBT/AES": "peasant's",
"AO*EUS/KW-BG": "eyes,",
"TPHOEPB": "known",
"TPRED/REUBG/KW-BG": "Frederick,",
"SEUL/SRER/KWREU": "silvery",
"HROBGZ": "locks",
"HOPBS": "honest",
"PWHRU": "blue",
"HREUFD": "lived",
"HEUPL/KW-BG": "him,",
"TPOELD/-D": "folded",
"HAPBDZ": "hands",
"SOPL": "some",
"TAOEUPL": "time",
"SHREPBT/TP-PL": "silent.",
"KAEUPL": "came",
"TKPWEGT": "getting",
"HRAEUT/KW-BG": "late,",
"OT": "ought",
"REFT": "rest",
"WHAOEUL/KW-BG": "while,",
"SAOURP": "supper",
"TAEUBL/TP-PL": "table.",
"KW-GS/KPA*/WHA": "\"What",
"U": "you",
"SR": "have",
"PW-PB": "been",
"PWAOUFL/KW-BG": "beautiful,",
"TKPWR-F/KW-BG/KR-GS": "grandfather,\"",
"SHE/TP-PL": "she.",
"KW-GS/H*P/O*/HR*/TKPW*/*ER": "\"Holger",
"ARPLS/STPH*FPLT": "arms;",
"SAOEPLS": "seems",
"PHE": "me",
"EU": "I",
"SAOEPB": "seen",
"TPAEUS": "face",
"SWR/TP-PL/KR-GS": "somewhere.\"",
"KW-GS/KPA*/TPHO/KW-BG": "\"No,",
"EUPL/POB/KW-BG/KR-GS": "impossible,\"",
"RE/PHRAOEUD": "replied",
"TKPWR-F/STPH*FPLT": "grandfather;",
"KW-GS/PWUT": "\"but",
"TRAOEUD": "tried",
"KAFRB": "carve",
"RAOE/TAEUPBD": "retained",
"PHOEURPL/TP-PL": "memory.",
"AG/KW-BG": "ago,",
"TKPWHREURB": "English",
"TPHRAOET": "fleet",
"RAODZ/KW-BG": "roads,",
"PREUL/KW-BG": "April,",
"WE": "we",
"SHOED": "showed",
"AEURBT": "ancient",
"TKA*EUPB/-S/TP-PL": "Danes.",
"PWAORD": "board",
"KPA/S*/T*/SKWR*E/*EPB/SKWR*E": "Steene",
"PW*EUL/SKWR*E/AES": "Bille's",
"SKWAD/ROPB/STPH*FPLT": "squadron;",
"SAOEUD": "side",
"WHOPL": "whom",
"KAPB/TPHOPB": "cannon",
"PWAULS": "balls",
"TPAOER/TP-PL": "fear.",
"SUPBG": "sung",
"SOPBGS": "songs",
"PHER/REU": "merry",
"SROEUS/KW-BG": "voice,",
"TPAOEURD": "fired",
"TPAUT": "fought",
"S-G": "something",
"STEUL": "still",
"RER": "remember",
"TPAEUS/KW-BG": "face,",
"TPR": "from",
"WHEPBS": "whence",
"KAEUPL/KW-BG": "came,",
"OR": "or",
"WEPBT/KW-BG": "went,",
"TPHOE": "know",
"TPHOT/STPH*FPLT": "not;",
"TPHOEZ/TP-PL": "knows.",
"OFPB": "often",
"PHAOEUT": "might",
"SWAPL": "swam",
"US": "us",
"K*P/R*/KWRO/*PB/*EPB/PW*URG": "Kronenburg",
"HEP": "help",
"HOUR": "hour",
"TKAEUPBLG/TP-PL": "danger.",
"KPA/THA": "That",
"KWR-D/KW-BG": "idea,",
"HRAOEUBG/-PBS/TP-PL/KR-GS": "likeness.\"",
"WAOD/EPB": "wooden",
"TPEUG": "figure",
"THRAOU": "threw",
"SKWRAOEU/TKPWAPBT/EUBG": "gigantic",
"SHOEUD": "shadow",
"WAUL/KW-BG": "wall,",
"KAOELG/STPH*FPLT": "ceiling;",
"HEUPBD": "behind",
"PHOFD/STPH*FPLT": "moved;",
"TKOUT": "doubt",
"KAUFD": "caused",
"HRAFRP": "lamp",
"PWURPBG": "burning",
"STED/HREU/TP-PL": "steadily.",
"TKAURPBL": "daughter-in-law",
"K*EUFD": "kissed",
"ARPL/H-PB/KHAEUR": "arm-chair",
"TAEUBL/STPH*FPLT": "table;",
"SHE/KW-BG": "she,",
"HUS/KW-BG": "husband,",
"SOPB": "son",
"TPAER": "father",
"TAUBGD": "talked",
"EPL/PWHREPL/-S": "emblems",
"STREPBG": "strength",
"SKWR*EPBLT/-PBS/KW-BG": "gentleness,",
"SPHRAEUPBD": "explained",
"KAOERL": "clearly",
"HRAO*EUS": "lies",
"SWORD/KW-BG": "sword,",
"POEUPBTD": "pointed",
"SHEFL": "shelf",
"TPHUPL": "number",
"PWAOBGS/KW-BG": "books,",
"PHOPBGS": "amongst",
"KHREBGS": "collection",
"H*P/HRO*/PWERG/AES": "Holberg's",
"PHRAEUZ/KW-BG": "plays,",
"R": "are",
"RAED": "read",
"KHREFR": "clever",
"A/PHAOUFG": "amusing",
"EZ": "easy",
"TPAEPBS": "fancy",
"PAOEPL": "people",
"THOZ": "those",
"TKAEUS/KW-BG": "days,",
"KREUFD": "described",
"KW-GS/KPA*/HE": "\"He",
"HOU": "how",
"TPAOEUT": "fight",
"HR-S/KW-BG/KR-GS": "also,\"",
"PHAPB/STPH*FPLT": "man;",
"KW-GS/TPOR": "\"for",
"HRARBD": "lashed",
"HRO*ER/TP*P/O*/HR*/HR*/*EU/*E/S*": "follies",
"PREPBLG/TKEUS/-S": "prejudices",
"TKURG": "during",
"HRAOEUF/TP-PL/KR-GS": "life.\"",
"PHRAEUS": "place",
"PWOF": "above",
"HRAOG/H-PB/TKPWHRAS/KW-BG": "looking-glass,",
"HUPBG": "hung",
"AUPL/TPHABG/KW-BG": "almanac,",
"REPGS": "representation",
"KPA/ROUPBD": "Round",
"KPA/TOUR": "Tower",
"KW-GS/KPA/TAO*E/*FP/KWRO": "\"Tycho",
"PW*P/R*/A*/H*/SKWR*E": "Brahe",
"AOUFD": "used",
"KUT": "cut",
"TPHRERB": "flesh",
"PWOEPB/KW-BG": "bone,",
"PHAEUBG": "make",
"WAEU": "way",
"STARS": "stars",
"HEFPB": "heaven",
"KHRAOER/KW-BG": "clear,",
"PHRAEUPB": "plain",
"*URPBD/TP-PL": "understood.",
"WHOZ": "whose",
"PWHROPBGD": "belonged",
"KAULG/KW-BG/EPL/TKA*RB/KWRERBGS": "calling,—yes,",
"HE/KW-BG": "he,",
"EUPBLG/H-PB/KAFRB/ER/KW-BG": "image-carver,",
"O*URSZ": "ourselves",
"SAOEPB/KW-BG": "seen,",
"SHOURLDZ/KW-BG": "shoulders,",
"HRAPBDZ/STPH*FPLT/EPL/TKA*RB/KWRERBGS": "lands;—yes,",
"SKAO*UFP/KW-BG": "sculptor,",
"APL": "am",
"KAFRB/ER/TP-PL": "carver.",
"K": "can",
"PHAERBL/KW-BG": "marble,",
"WORLD": "world",
"HAER": "hear",
"KPA/TPHOU": "Now",
"HRET": "let",
"TKREU": "drink",
"H*ELT": "health",
"PW*P/*E/R*/T*/*E/HR*/TP-PL/KR-GS": "Bertel.\"",
"SAU": "saw",
"PHRAEUPBL": "plainly",
"TKRAOEPLG": "dreaming",
"PAFG": "passing",
"TK": "did",
"TKRAOEPL": "dream",
"EUPBLG/H-PB/KAFRB/ER": "image-carver",
"SAT/STPH*FPLT": "sat;",
"TKRAOEPL/KW-BG": "dream,",
"SAEUG/KW-BG": "saying,",
"KWRERBGS": "yes,",
"PHE/KW-BG": "me,",
"PAOEPL/KW-BG": "people,",
"KAOEP": "keep",
"KWROUR": "your",
"PHOEURPL/KW-BG": "memory,",
"TPHAOED/TP-PL/KR-GS": "need.\"",
"PWRAOEUT": "bright",
"PHORPBG": "morning",
"HRAOEUT": "light",
"SHO*EPB": "shone",
"OEFR": "over",
"WEUPBD": "wind",
"PWRAUT": "brought",
"HUPBT/-G/H-PB/HORPB": "hunting-horn",
"KRAOS": "across",
"TPHAEUB/-G": "neighboring",
"SHORS/TP-PL": "shores.",
"SAEULD": "sailed",
"SA/HRAOUT/-D": "saluted",
"PWAOPL": "boom",
"KAPB/TPHOPB/KW-BG": "cannon,",
"RURPBD": "returned",
"SA/HRAOUT/KW-BG": "salute,",
"PWAOPL/TP-PL/KR-GS": "boom.\"",
"RAORG": "roaring",
"A/WAEUBG": "awake",
"PHEPBT": "meant",
"KW-GS/KPA*/TKPWAOD": "\"Good",
"PHORPBG/KW-BG/KR-GS": "morning,\"",
"U/TP-PL/KR-GS": "you.\"",
"KPA/THE": "They",
"TPAOEUR": "fire",
"TPAGS": "fashion",
"PW-FR": "before",
"A/WAEUBGS/STPH*FPLT": "awakes;",
"WAEUBG": "wake",
"HR-RBGS": "will,",
"TPH-RG": "energy",
"TKAPB/-S/*BG/SKWR*E/TP-PL": "Danske."
}
